{
	"name": "Project-Move5-File-Pipeline",
	"properties": {
		"activities": [
			{
				"name": "Get Metadata1",
				"type": "GetMetadata",
				"dependsOn": [],
				"policy": {
					"timeout": "7.00:00:00",
					"retry": 0,
					"retryIntervalInSeconds": 30,
					"secureOutput": false,
					"secureInput": false
				},
				"userProperties": [],
				"typeProperties": {
					"dataset": {
						"referenceName": "SourceOutputfeed",
						"type": "DatasetReference"
					},
					"fieldList": [
						"childItems",
						"exists",
						"itemName",
						"itemType",
						"lastModified"
					],
					"storeSettings": {
						"type": "AzureBlobFSReadSettings",
						"recursive": true,
						"enablePartitionDiscovery": false
					},
					"formatSettings": {
						"type": "DelimitedTextReadSettings"
					}
				}
			},
			{
				"name": "ForEach1",
				"type": "ForEach",
				"dependsOn": [
					{
						"activity": "Get Metadata1",
						"dependencyConditions": [
							"Succeeded"
						]
					}
				],
				"userProperties": [],
				"typeProperties": {
					"items": {
						"value": "@activity('Get Metadata1').output.childItems",
						"type": "Expression"
					},
					"isSequential": true,
					"activities": [
						{
							"name": "Copy data1",
							"type": "Copy",
							"dependsOn": [],
							"policy": {
								"timeout": "7.00:00:00",
								"retry": 0,
								"retryIntervalInSeconds": 30,
								"secureOutput": false,
								"secureInput": false
							},
							"userProperties": [],
							"typeProperties": {
								"source": {
									"type": "DelimitedTextSource",
									"storeSettings": {
										"type": "AzureBlobFSReadSettings",
										"recursive": true,
										"enablePartitionDiscovery": false
									},
									"formatSettings": {
										"type": "DelimitedTextReadSettings"
									}
								},
								"sink": {
									"type": "AzureSqlSink",
									"preCopyScript": {
										"value": "truncate table dbo.Customer;",
										"type": "Expression"
									},
									"disableMetricsCollection": false
								},
								"enableStaging": false,
								"translator": {
									"type": "TabularTranslator",
									"typeConversion": true,
									"typeConversionSettings": {
										"allowDataTruncation": true,
										"treatBooleanAsNumber": false
									}
								}
							},
							"inputs": [
								{
									"referenceName": "ProjDelimitedText",
									"type": "DatasetReference",
									"parameters": {
										"container": {
											"value": "@pipeline().parameters.container",
											"type": "Expression"
										},
										"folder": {
											"value": "@pipeline().parameters.Folder",
											"type": "Expression"
										},
										"file": {
											"value": "@item().name",
											"type": "Expression"
										}
									}
								}
							],
							"outputs": [
								{
									"referenceName": "sinkSQLtable",
									"type": "DatasetReference"
								}
							]
						}
					]
				}
			},
			{
				"name": "Copy data2",
				"type": "Copy",
				"dependsOn": [
					{
						"activity": "ForEach1",
						"dependencyConditions": [
							"Succeeded"
						]
					}
				],
				"policy": {
					"timeout": "7.00:00:00",
					"retry": 0,
					"retryIntervalInSeconds": 30,
					"secureOutput": false,
					"secureInput": false
				},
				"userProperties": [],
				"typeProperties": {
					"source": {
						"type": "AzureSqlSource",
						"queryTimeout": "02:00:00",
						"partitionOption": "None"
					},
					"sink": {
						"type": "SqlServerSink",
						"preCopyScript": {
							"value": "truncate table dbo.Customer;",
							"type": "Expression"
						}
					},
					"enableStaging": false,
					"translator": {
						"type": "TabularTranslator",
						"typeConversion": true,
						"typeConversionSettings": {
							"allowDataTruncation": true,
							"treatBooleanAsNumber": false
						}
					}
				},
				"inputs": [
					{
						"referenceName": "sinkSQLtable",
						"type": "DatasetReference"
					}
				],
				"outputs": [
					{
						"referenceName": "onPremSQLserver",
						"type": "DatasetReference"
					}
				]
			}
		],
		"parameters": {
			"container": {
				"type": "string",
				"defaultValue": "karthiccontainer"
			},
			"Folder": {
				"type": "string",
				"defaultValue": "outputfeed"
			},
			"File": {
				"type": "string"
			},
			"ArchiveFolder": {
				"type": "string",
				"defaultValue": "archievefeed"
			},
			"ErrorFolder": {
				"type": "string",
				"defaultValue": "errorfeed"
			},
			"dbconnection": {
				"type": "string",
				"defaultValue": "gsk-az-sql-server.database.windows.net"
			},
			"dbname": {
				"type": "string",
				"defaultValue": "karthic-az-db"
			},
			"dbtable": {
				"type": "string",
				"defaultValue": "dbo.Customer"
			}
		},
		"folder": {
			"name": "oct16-pipeline"
		},
		"annotations": []
	}
}